appel_crises/__init__.py
appel_crises/admin.py
appel_crises/api.py
appel_crises/asgi.py
appel_crises/captcha.py
appel_crises/challenges.py
appel_crises/mailer.py
appel_crises/models.py
appel_crises/settings.py
appel_crises/tests.py
appel_crises/urls.py
appel_crises/views.py
appel_crises/wsgi.py
appel_crises/assets/staticfiles.json
appel_crises/assets/admin/css/autocomplete.781713f30664.css
appel_crises/assets/admin/css/autocomplete.781713f30664.css.br
appel_crises/assets/admin/css/autocomplete.781713f30664.css.gz
appel_crises/assets/admin/css/autocomplete.css
appel_crises/assets/admin/css/autocomplete.css.br
appel_crises/assets/admin/css/autocomplete.css.gz
appel_crises/assets/admin/css/base.css
appel_crises/assets/admin/css/base.css.br
appel_crises/assets/admin/css/base.css.gz
appel_crises/assets/admin/css/base.efb520c4bb7c.css
appel_crises/assets/admin/css/base.efb520c4bb7c.css.br
appel_crises/assets/admin/css/base.efb520c4bb7c.css.gz
appel_crises/assets/admin/css/changelists.09730d6ad169.css
appel_crises/assets/admin/css/changelists.09730d6ad169.css.br
appel_crises/assets/admin/css/changelists.09730d6ad169.css.gz
appel_crises/assets/admin/css/changelists.css
appel_crises/assets/admin/css/changelists.css.br
appel_crises/assets/admin/css/changelists.css.gz
appel_crises/assets/admin/css/dashboard.be83f13e4369.css
appel_crises/assets/admin/css/dashboard.be83f13e4369.css.br
appel_crises/assets/admin/css/dashboard.be83f13e4369.css.gz
appel_crises/assets/admin/css/dashboard.css
appel_crises/assets/admin/css/dashboard.css.br
appel_crises/assets/admin/css/dashboard.css.gz
appel_crises/assets/admin/css/fonts.168bab448fee.css
appel_crises/assets/admin/css/fonts.168bab448fee.css.br
appel_crises/assets/admin/css/fonts.168bab448fee.css.gz
appel_crises/assets/admin/css/fonts.css
appel_crises/assets/admin/css/fonts.css.br
appel_crises/assets/admin/css/fonts.css.gz
appel_crises/assets/admin/css/forms.6230fc2a74ac.css
appel_crises/assets/admin/css/forms.6230fc2a74ac.css.br
appel_crises-0.0.37.dist-info/LICENSE
appel_crises-0.0.37.dist-info/METADATA
appel_crises-0.0.37.dist-info/WHEEL
appel_crises-0.0.37.dist-info/top_level.txt
appel_crises-0.0.37.dist-info/RECORD
