Metadata-Version: 2.1
Name: appel-crises
Version: 0.0.37
Summary: Website for the `appel-crises` petition
Home-page: https://pypi.org/project/appel-crises
Author: Pour Un Réveil Écologique
License: AGPL-3
Keywords: petition,ecology
Platform: UNKNOWN
Classifier: Development Status :: 3 - Alpha
Classifier: Framework :: Django
Classifier: License :: OSI Approved :: GNU Affero General Public License v3
Classifier: Natural Language :: French
Classifier: Operating System :: OS Independent
Classifier: Programming Language :: Python :: 3.7
Requires-Python: >=3.7
Requires-Dist: django (>=3.0)
Requires-Dist: importlib-metadata
Requires-Dist: psycopg2
Requires-Dist: getconf
Requires-Dist: whitenoise[brotli]
Requires-Dist: requests
Requires-Dist: sentry-sdk (==0.14.3)
Provides-Extra: dev
Requires-Dist: check-manifest ; extra == 'dev'
Requires-Dist: flake8 ; extra == 'dev'
Requires-Dist: pre-commit ; extra == 'dev'
Requires-Dist: openpyxl ; extra == 'dev'
Requires-Dist: tqdm ; extra == 'dev'
Requires-Dist: zest.releaser[recommended] ; extra == 'dev'
